ecotrade/authentication.py
ecotrade/comunications.py
ecotrade/database.py
ecotrade/hermes_access.py
ecotrade/logs.py
ecotrade/sharepoint.py
ecotrade/utils.py
ecotrade-1.3.4.dist-info/LICENSE
ecotrade-1.3.4.dist-info/METADATA
ecotrade-1.3.4.dist-info/WHEEL
ecotrade-1.3.4.dist-info/top_level.txt
ecotrade-1.3.4.dist-info/RECORD
