Metadata-Version: 2.2
Name: ecotrade
Version: 1.3.4
Summary: An Ecotrade package to manage the software infrastructure
Author: Zyber Pireci & Vishva Teja Janne
Author-email: supporto@ecotrade.bio
License: MIT
Classifier: Programming Language :: Python :: 3
Classifier: License :: OSI Approved :: MIT License
Classifier: Operating System :: OS Independent
Requires-Python: >=3.6
License-File: LICENSE
Requires-Dist: requests
Requires-Dist: pyodbc
Dynamic: author
Dynamic: author-email
Dynamic: classifier
Dynamic: description
Dynamic: description-content-type
Dynamic: license
Dynamic: requires-dist
Dynamic: requires-python
Dynamic: summary
